{"playerId":8478585,"isActive":true,"currentTeamId":22,"currentTeamAbbrev":"EDM","fullTeamName":{"default":"Edmonton Oilers","fr":"Oilers d'Edmonton"},"firstName":{"default":"Derek"},"lastName":{"default":"Ryan"},"teamLogo":"https://assets.nhle.com/logos/nhl/svg/EDM_light.svg","sweaterNumber":10,"position":"C","headshot":"https://assets.nhle.com/mugs/nhl/20232024/EDM/8478585.png","heroImage":"https://assets.nhle.com/mugs/actionshots/1296x729/8478585.jpg","heightInInches":70,"heightInCentimeters":178,"weightInPounds":185,"weightInKilograms":84,"birthDate":"1986-12-29","birthCity":{"default":"Spokane"},"birthStateProvince":{"default":"Washington"},"birthCountry":"USA","shootsCatches":"R","playerSlug":"derek-ryan-8478585","inTop100AllTime":0,"inHHOF":0,"featuredStats":{"season":20232024,"regularSeason":{"subSeason":{"gamesPlayed":28,"goals":3,"assists":4,"points":7,"plusMinus":1,"pim":2,"gameWinningGoals":0,"otGoals":0,"shots":21,"shootingPctg":0.142857,"powerPlayGoals":0,"powerPlayPoints":0,"shorthandedGoals":1,"shorthandedPoints":2},"career":{"gamesPlayed":528,"goals":79,"assists":119,"points":198,"plusMinus":22,"pim":140,"gameWinningGoals":7,"otGoals":0,"shots":640,"shootingPctg":0.1234,"powerPlayGoals":11,"powerPlayPoints":27,"shorthandedGoals":5,"shorthandedPoints":13}}},"careerTotals":{"regularSeason":{"gamesPlayed":528,"goals":79,"assists":119,"pim":140,"points":198,"plusMinus":22,"powerPlayGoals":11,"powerPlayPoints":27,"shorthandedPoints":13,"gameWinningGoals":7,"otGoals":0,"shots":640,"shootingPctg":0.1234,"faceoffWinningPctg":0.5493,"avgToi":"13:12","shorthandedGoals":5},"playoffs":{"gamesPlayed":41,"goals":3,"assists":6,"pim":6,"points":9,"plusMinus":4,"powerPlayGoals":0,"powerPlayPoints":0,"shorthandedPoints":1,"gameWinningGoals":0,"otGoals":0,"shots":43,"shootingPctg":0.0697,"faceoffWinningPctg":0.5265,"avgToi":"11:35","shorthandedGoals":0}},"shopLink":"#TODO","twitterLink":"#TODO","watchLink":"#TODO","last5Games":[{"gameId":2023020472,"gameTypeId":2,"teamAbbrev":"EDM","homeRoadFlag":"H","gameDate":"2023-12-16","goals":0,"assists":0,"points":0,"plusMinus":0,"powerPlayGoals":0,"shots":0,"shifts":8,"shorthandedGoals":0,"pim":0,"opponentAbbrev":"FLA","toi":"5:39"},{"gameId":2023020452,"gameTypeId":2,"teamAbbrev":"EDM","homeRoadFlag":"H","gameDate":"2023-12-14","goals":0,"assists":1,"points":1,"plusMinus":0,"powerPlayGoals":0,"shots":1,"shifts":14,"shorthandedGoals":0,"pim":0,"opponentAbbrev":"TBL","toi":"8:04"},{"gameId":2023020437,"gameTypeId":2,"teamAbbrev":"EDM","homeRoadFlag":"H","gameDate":"2023-12-12","goals":0,"assists":1,"points":1,"plusMinus":1,"powerPlayGoals":0,"shots":0,"shifts":15,"shorthandedGoals":0,"pim":0,"opponentAbbrev":"CHI","toi":"11:23"},{"gameId":2023020421,"gameTypeId":2,"teamAbbrev":"EDM","homeRoadFlag":"H","gameDate":"2023-12-10","goals":1,"assists":0,"points":1,"plusMinus":1,"powerPlayGoals":0,"shots":2,"shifts":16,"shorthandedGoals":0,"pim":0,"opponentAbbrev":"NJD","toi":"9:43"},{"gameId":2023020407,"gameTypeId":2,"teamAbbrev":"EDM","homeRoadFlag":"H","gameDate":"2023-12-08","goals":0,"assists":0,"points":0,"plusMinus":-1,"powerPlayGoals":0,"shots":1,"shifts":15,"shorthandedGoals":0,"pim":0,"opponentAbbrev":"MIN","toi":"10:26"}],"seasonTotals":[{"season":20022003,"gameTypeId":2,"leagueAbbrev":"KIJHL","teamName":{"default":"Spokane Braves"},"sequence":36776,"gamesPlayed":49,"goals":26,"assists":29,"points":55,"pim":24},{"season":20022003,"gameTypeId":3,"leagueAbbrev":"KIJHL","teamName":{"default":"Spokane Braves"},"sequence":36776,"gamesPlayed":6,"goals":3,"assists":5,"points":8,"pim":0},{"season":20032004,"gameTypeId":2,"leagueAbbrev":"WHL","teamName":{"default":"Spokane Chiefs"},"sequence":6916,"gamesPlayed":1,"goals":1,"assists":0,"points":1,"plusMinus":1,"pim":0},{"season":20032004,"gameTypeId":3,"leagueAbbrev":"WHL","teamName":{"default":"Spokane Chiefs"},"sequence":7901,"gamesPlayed":4,"goals":1,"assists":0,"points":1,"plusMinus":-3,"pim":0},{"season":20032004,"gameTypeId":3,"leagueAbbrev":"KIJHL","teamName":{"default":"Spokane Braves"},"sequence":36776,"gamesPlayed":7,"goals":5,"assists":10,"points":15},{"season":20042005,"gameTypeId":2,"leagueAbbrev":"WHL","teamName":{"default":"Spokane Chiefs"},"sequence":6916,"gamesPlayed":71,"goals":14,"assists":32,"points":46,"plusMinus":-11,"pim":39},{"season":20052006,"gameTypeId":2,"leagueAbbrev":"WHL","teamName":{"default":"Spokane Chiefs"},"sequence":6916,"gamesPlayed":72,"goals":24,"assists":37,"points":61,"plusMinus":-6,"pim":50},{"season":20062007,"gameTypeId":2,"leagueAbbrev":"WHL","teamName":{"default":"Spokane Chiefs"},"sequence":6916,"gamesPlayed":72,"goals":28,"assists":31,"points":59,"plusMinus":-2,"pim":50},{"season":20062007,"gameTypeId":3,"leagueAbbrev":"WHL","teamName":{"default":"Spokane Chiefs"},"sequence":7901,"gamesPlayed":6,"goals":3,"assists":2,"points":5,"plusMinus":-3,"pim":2},{"season":20062007,"gameTypeId":3,"leagueAbbrev":"UHL","teamName":{"default":"Kalamazoo Wings"},"sequence":8779,"gamesPlayed":13,"goals":4,"assists":1,"points":5,"plusMinus":-1,"pim":8},{"season":20072008,"gameTypeId":2,"leagueAbbrev":"USports","teamName":{"default":"Univ. of Alberta"},"sequence":10094725,"gamesPlayed":28,"goals":11,"assists":14,"points":25,"plusMinus":4,"pim":20},{"season":20082009,"gameTypeId":2,"leagueAbbrev":"USports","teamName":{"default":"Univ. of Alberta"},"sequence":10094725,"gamesPlayed":25,"goals":16,"assists":19,"points":35,"plusMinus":17,"pim":16},{"season":20082009,"gameTypeId":3,"leagueAbbrev":"USports","teamName":{"default":"Univ. of Alberta"},"sequence":12772,"gamesPlayed":5,"goals":1,"assists":6,"points":7,"plusMinus":7,"pim":2},{"season":20092010,"gameTypeId":2,"leagueAbbrev":"USports","teamName":{"default":"Univ. of Alberta"},"sequence":10094725,"gamesPlayed":28,"goals":14,"assists":25,"points":39,"plusMinus":6,"pim":30},{"season":20092010,"gameTypeId":3,"leagueAbbrev":"USports","teamName":{"default":"Univ. of Alberta"},"sequence":12772,"gamesPlayed":5,"goals":0,"assists":2,"points":2,"plusMinus":-1,"pim":0},{"season":20102011,"gameTypeId":2,"leagueAbbrev":"USports","teamName":{"default":"Univ. of Alberta"},"sequence":10094725,"gamesPlayed":28,"goals":17,"assists":30,"points":47,"plusMinus":25,"pim":18},{"season":20102011,"gameTypeId":3,"leagueAbbrev":"USports","teamName":{"default":"Univ. of Alberta"},"sequence":12772,"gamesPlayed":4,"goals":4,"assists":5,"points":9,"plusMinus":7,"pim":0},{"season":20112012,"gameTypeId":2,"leagueAbbrev":"Austria","teamName":{"default":"Szekesfehervar"},"sequence":1,"gamesPlayed":50,"goals":25,"assists":24,"points":49,"plusMinus":3,"pim":20},{"season":20112012,"gameTypeId":3,"leagueAbbrev":"Austria","teamName":{"default":"Szekesfehervar"},"sequence":1,"gamesPlayed":6,"goals":1,"assists":3,"points":4,"plusMinus":2,"pim":6},{"season":20122013,"gameTypeId":2,"leagueAbbrev":"Austria","teamName":{"default":"Villach"},"sequence":1,"gamesPlayed":54,"goals":27,"assists":39,"points":66,"plusMinus":16,"pim":22},{"season":20122013,"gameTypeId":3,"leagueAbbrev":"Austria","teamName":{"default":"Villach"},"sequence":1,"gamesPlayed":7,"goals":3,"assists":8,"points":11,"plusMinus":-3,"pim":6},{"season":20132014,"gameTypeId":2,"leagueAbbrev":"Austria","teamName":{"default":"Villach"},"sequence":1,"gamesPlayed":54,"goals":38,"assists":46,"points":84,"pim":50},{"season":20132014,"gameTypeId":3,"leagueAbbrev":"ICEHL","teamName":{"default":"Villacher SV"},"sequence":2658,"gamesPlayed":9,"goals":2,"assists":14,"points":16,"plusMinus":6,"pim":6},{"season":20142015,"gameTypeId":2,"leagueAbbrev":"Sweden","teamName":{"default":"Orebro"},"sequence":1,"gamesPlayed":55,"goals":15,"assists":45,"points":60,"pim":18},{"season":20142015,"gameTypeId":3,"leagueAbbrev":"Sweden","teamName":{"default":"Orebro"},"sequence":1,"gamesPlayed":6,"goals":0,"assists":1,"points":1,"pim":2},{"season":20152016,"gameTypeId":2,"leagueAbbrev":"NHL","teamName":{"default":"Carolina Hurricanes","fr":"Hurricanes de la Caroline"},"sequence":1,"gamesPlayed":6,"goals":2,"assists":0,"points":2,"plusMinus":1,"powerPlayGoals":1,"powerPlayPoints":1,"shorthandedPoints":0,"gameWinningGoals":0,"otGoals":0,"shots":5,"shootingPctg":0.4,"faceoffWinningPctg":0.5932,"avgToi":"12:12","shorthandedGoals":0,"pim":2},{"season":20152016,"gameTypeId":2,"leagueAbbrev":"AHL","teamName":{"default":"Charlotte"},"sequence":2,"gamesPlayed":70,"goals":23,"assists":32,"points":55,"plusMinus":5,"powerPlayGoals":7,"gameWinningGoals":4,"shots":161,"shootingPctg":14.3,"shorthandedGoals":0,"pim":24},{"season":20162017,"gameTypeId":2,"leagueAbbrev":"NHL","teamName":{"default":"Carolina Hurricanes","fr":"Hurricanes de la Caroline"},"sequence":1,"gamesPlayed":67,"goals":11,"assists":18,"points":29,"plusMinus":-8,"powerPlayGoals":4,"powerPlayPoints":8,"shorthandedPoints":1,"gameWinningGoals":3,"otGoals":0,"shots":73,"shootingPctg":0.1507,"faceoffWinningPctg":0.553,"avgToi":"14:53","shorthandedGoals":1,"pim":22},{"season":20162017,"gameTypeId":2,"leagueAbbrev":"AHL","teamName":{"default":"Charlotte Checkers"},"sequence":2357,"gamesPlayed":9,"goals":5,"assists":8,"points":13,"plusMinus":4,"pim":0},{"season":20172018,"gameTypeId":2,"leagueAbbrev":"NHL","teamName":{"default":"Carolina Hurricanes","fr":"Hurricanes de la Caroline"},"sequence":1,"gamesPlayed":80,"goals":15,"assists":23,"points":38,"plusMinus":-15,"powerPlayGoals":3,"powerPlayPoints":7,"shorthandedPoints":0,"gameWinningGoals":1,"otGoals":0,"shots":135,"shootingPctg":0.1111,"faceoffWinningPctg":0.5649,"avgToi":"15:36","shorthandedGoals":0,"pim":28},{"season":20172018,"gameTypeId":2,"leagueAbbrev":"WC","teamName":{"default":"USA","fr":"États-Unis"},"sequence":17215,"gamesPlayed":10,"goals":4,"assists":3,"points":7,"plusMinus":3,"pim":0},{"season":20182019,"gameTypeId":2,"leagueAbbrev":"NHL","teamName":{"default":"Calgary Flames","fr":"Flames de Calgary"},"sequence":1,"gamesPlayed":81,"goals":13,"assists":25,"points":38,"plusMinus":21,"powerPlayGoals":2,"powerPlayPoints":7,"shorthandedPoints":4,"gameWinningGoals":1,"otGoals":0,"shots":103,"shootingPctg":0.1262,"faceoffWinningPctg":0.582,"avgToi":"13:48","shorthandedGoals":0,"pim":24},{"season":20182019,"gameTypeId":2,"leagueAbbrev":"WC","teamName":{"default":"USA","fr":"États-Unis"},"sequence":17215,"gamesPlayed":7,"goals":1,"assists":3,"points":4,"plusMinus":3,"pim":2},{"season":20182019,"gameTypeId":3,"leagueAbbrev":"NHL","teamName":{"default":"Calgary Flames","fr":"Flames de Calgary"},"sequence":1,"gamesPlayed":5,"goals":1,"assists":0,"points":1,"plusMinus":1,"powerPlayGoals":0,"powerPlayPoints":0,"shorthandedPoints":0,"gameWinningGoals":0,"otGoals":0,"shots":4,"shootingPctg":0.25,"faceoffWinningPctg":0.5932,"avgToi":"14:14","shorthandedGoals":0,"pim":2},{"season":20192020,"gameTypeId":2,"leagueAbbrev":"NHL","teamName":{"default":"Calgary Flames","fr":"Flames de Calgary"},"sequence":1,"gamesPlayed":68,"goals":10,"assists":19,"points":29,"plusMinus":9,"powerPlayGoals":1,"powerPlayPoints":4,"shorthandedPoints":2,"gameWinningGoals":0,"otGoals":0,"shots":102,"shootingPctg":0.098,"faceoffWinningPctg":0.5232,"avgToi":"14:32","shorthandedGoals":1,"pim":10},{"season":20192020,"gameTypeId":3,"leagueAbbrev":"NHL","teamName":{"default":"Calgary Flames","fr":"Flames de Calgary"},"sequence":1,"gamesPlayed":10,"goals":0,"assists":2,"points":2,"plusMinus":3,"powerPlayGoals":0,"powerPlayPoints":0,"shorthandedPoints":1,"gameWinningGoals":0,"otGoals":0,"shots":8,"shootingPctg":0.0,"faceoffWinningPctg":0.4348,"avgToi":"10:40","shorthandedGoals":0,"pim":0},{"season":20202021,"gameTypeId":2,"leagueAbbrev":"NHL","teamName":{"default":"Calgary Flames","fr":"Flames de Calgary"},"sequence":1,"gamesPlayed":43,"goals":2,"assists":11,"points":13,"plusMinus":6,"powerPlayGoals":0,"powerPlayPoints":0,"shorthandedPoints":0,"gameWinningGoals":0,"otGoals":0,"shots":37,"shootingPctg":0.054,"faceoffWinningPctg":0.5204,"avgToi":"11:53","shorthandedGoals":0,"pim":16},{"season":20212022,"gameTypeId":2,"leagueAbbrev":"NHL","teamName":{"default":"Edmonton Oilers","fr":"Oilers d'Edmonton"},"sequence":1,"gamesPlayed":75,"goals":10,"assists":12,"points":22,"plusMinus":-4,"powerPlayGoals":0,"powerPlayPoints":0,"shorthandedPoints":1,"gameWinningGoals":2,"otGoals":0,"shots":72,"shootingPctg":0.139,"faceoffWinningPctg":0.558594,"avgToi":"11:25","shorthandedGoals":0,"pim":8},{"season":20212022,"gameTypeId":3,"leagueAbbrev":"NHL","teamName":{"default":"Edmonton Oilers","fr":"Oilers d'Edmonton"},"sequence":1,"gamesPlayed":15,"goals":1,"assists":2,"points":3,"plusMinus":-3,"powerPlayGoals":0,"powerPlayPoints":0,"shorthandedPoints":0,"gameWinningGoals":0,"otGoals":0,"shots":12,"shootingPctg":0.083,"faceoffWinningPctg":0.562044,"avgToi":"11:08","shorthandedGoals":0,"pim":4},{"season":20222023,"gameTypeId":2,"leagueAbbrev":"NHL","teamName":{"default":"Edmonton Oilers","fr":"Oilers d'Edmonton"},"sequence":1,"gamesPlayed":80,"goals":13,"assists":7,"points":20,"plusMinus":11,"powerPlayGoals":0,"powerPlayPoints":0,"shorthandedPoints":3,"gameWinningGoals":0,"otGoals":0,"shots":92,"shootingPctg":0.141304,"faceoffWinningPctg":0.5,"avgToi":"11:09","shorthandedGoals":2,"pim":28},{"season":20222023,"gameTypeId":3,"leagueAbbrev":"NHL","teamName":{"default":"Edmonton Oilers","fr":"Oilers d'Edmonton"},"sequence":1,"gamesPlayed":11,"goals":1,"assists":2,"points":3,"plusMinus":3,"powerPlayGoals":0,"powerPlayPoints":0,"shorthandedPoints":0,"gameWinningGoals":0,"otGoals":0,"shots":19,"shootingPctg":0.052632,"faceoffWinningPctg":0.388889,"avgToi":"11:50","shorthandedGoals":0,"pim":0},{"season":20232024,"gameTypeId":2,"leagueAbbrev":"NHL","teamName":{"default":"Edmonton Oilers","fr":"Oilers d'Edmonton"},"sequence":1,"gamesPlayed":28,"goals":3,"assists":4,"points":7,"plusMinus":1,"powerPlayGoals":0,"powerPlayPoints":0,"shorthandedPoints":2,"gameWinningGoals":0,"otGoals":0,"shots":21,"shootingPctg":0.142857,"faceoffWinningPctg":0.548387,"avgToi":"10:07","shorthandedGoals":1,"pim":2}],"currentTeamRoster":[{"playerId":8480803,"lastName":{"default":"Bouchard"},"firstName":{"default":"Evan"},"playerSlug":"evan-bouchard-8480803"},{"playerId":8477015,"lastName":{"default":"Brown"},"firstName":{"default":"Connor"},"playerSlug":"connor-brown-8477015"},{"playerId":8476879,"lastName":{"default":"Ceci"},"firstName":{"default":"Cody"},"playerSlug":"cody-ceci-8476879"},{"playerId":8479576,"lastName":{"default":"Desharnais"},"firstName":{"default":"Vincent"},"playerSlug":"vincent-desharnais-8479576"},{"playerId":8477934,"lastName":{"default":"Draisaitl"},"firstName":{"default":"Leon"},"playerSlug":"leon-draisaitl-8477934"},{"playerId":8475218,"lastName":{"default":"Ekholm"},"firstName":{"default":"Mattias"},"playerSlug":"mattias-ekholm-8475218"},{"playerId":8477454,"lastName":{"default":"Erne"},"firstName":{"default":"Adam"},"playerSlug":"adam-erne-8477454"},{"playerId":8477998,"lastName":{"default":"Foegele"},"firstName":{"default":"Warren"},"playerSlug":"warren-foegele-8477998"},{"playerId":8474040,"lastName":{"default":"Gagner"},"firstName":{"default":"Sam"},"playerSlug":"sam-gagner-8474040"},{"playerId":8479416,"lastName":{"default":"Gleason"},"firstName":{"default":"Ben"},"playerSlug":"ben-gleason-8479416"},{"playerId":8480468,"lastName":{"default":"Hamblin"},"firstName":{"default":"James"},"playerSlug":"james-hamblin-8480468"},{"playerId":8482077,"lastName":{"default":"Holloway"},"firstName":{"default":"Dylan"},"playerSlug":"dylan-holloway-8482077"},{"playerId":8475786,"lastName":{"default":"Hyman"},"firstName":{"default":"Zach"},"playerSlug":"zach-hyman-8475786"},{"playerId":8477406,"lastName":{"default":"Janmark","sv":"Janmark-Nylén"},"firstName":{"default":"Mattias"},"playerSlug":"mattias-janmark-8477406"},{"playerId":8475169,"lastName":{"default":"Kane"},"firstName":{"default":"Evander"},"playerSlug":"evander-kane-8475169"},{"playerId":8476967,"lastName":{"default":"Kulak"},"firstName":{"default":"Brett"},"playerSlug":"brett-kulak-8476967"},{"playerId":8478402,"lastName":{"default":"McDavid"},"firstName":{"default":"Connor"},"playerSlug":"connor-mcdavid-8478402"},{"playerId":8480802,"lastName":{"default":"McLeod"},"firstName":{"default":"Ryan"},"playerSlug":"ryan-mcleod-8480802"},{"playerId":8476454,"lastName":{"default":"Nugent-Hopkins"},"firstName":{"default":"Ryan"},"playerSlug":"ryan-nugent-hopkins-8476454"},{"playerId":8477498,"lastName":{"default":"Nurse"},"firstName":{"default":"Darnell"},"playerSlug":"darnell-nurse-8477498"},{"playerId":8475717,"lastName":{"default":"Pickard"},"firstName":{"default":"Calvin"},"playerSlug":"calvin-pickard-8475717"},{"playerId":8478585,"lastName":{"default":"Ryan"},"firstName":{"default":"Derek"},"playerSlug":"derek-ryan-8478585"},{"playerId":8479973,"lastName":{"default":"Skinner"},"firstName":{"default":"Stuart"},"playerSlug":"stuart-skinner-8479973"}]}