{"playerId":8481043,"isActive":true,"currentTeamId":6,"currentTeamAbbrev":"BOS","fullTeamName":{"default":"Boston Bruins","fr":"Bruins de Boston"},"teamCommonName":{"default":"Bruins"},"teamPlaceNameWithPreposition":{"default":"Boston","fr":"de Boston"},"firstName":{"default":"Cole"},"lastName":{"default":"Koepke"},"teamLogo":"https://assets.nhle.com/logos/nhl/svg/BOS_light.svg","sweaterNumber":45,"position":"L","headshot":"https://assets.nhle.com/mugs/nhl/20242025/BOS/8481043.png","heroImage":"https://assets.nhle.com/mugs/actionshots/1296x729/8481043.jpg","heightInInches":73,"heightInCentimeters":185,"weightInPounds":203,"weightInKilograms":92,"birthDate":"1998-05-17","birthCity":{"default":"Two Harbors"},"birthStateProvince":{"default":"Minnesota"},"birthCountry":"USA","shootsCatches":"L","draftDetails":{"year":2018,"teamAbbrev":"TBL","round":6,"pickInRound":28,"overallPick":183},"playerSlug":"cole-koepke-8481043","inTop100AllTime":0,"inHHOF":0,"featuredStats":{"season":20232024,"regularSeason":{"subSeason":{"assists":2,"gameWinningGoals":0,"gamesPlayed":9,"goals":0,"otGoals":0,"pim":0,"plusMinus":0,"points":2,"powerPlayGoals":0,"powerPlayPoints":0,"shootingPctg":0.0,"shorthandedGoals":0,"shorthandedPoints":0,"shots":9},"career":{"assists":2,"gameWinningGoals":0,"gamesPlayed":26,"goals":1,"otGoals":0,"pim":2,"plusMinus":-5,"points":3,"powerPlayGoals":0,"powerPlayPoints":0,"shootingPctg":0.047599999999999996,"shorthandedGoals":0,"shorthandedPoints":0,"shots":21}}},"careerTotals":{"regularSeason":{"assists":2,"avgToi":"8:16","gameWinningGoals":0,"gamesPlayed":26,"goals":1,"otGoals":0,"pim":2,"plusMinus":-5,"points":3,"powerPlayGoals":0,"powerPlayPoints":0,"shootingPctg":0.047599999999999996,"shorthandedGoals":0,"shorthandedPoints":0,"shots":21}},"shopLink":"#TODO","twitterLink":"#TODO","watchLink":"#TODO","last5Games":[{"assists":0,"gameDate":"2024-02-22","gameId":2023020894,"gameTypeId":2,"goals":0,"homeRoadFlag":"H","opponentAbbrev":"WSH","pim":0,"plusMinus":0,"points":0,"powerPlayGoals":0,"shifts":11,"shorthandedGoals":0,"shots":2,"teamAbbrev":"TBL","toi":"5:59"},{"assists":0,"gameDate":"2023-12-09","gameId":2023020418,"gameTypeId":2,"goals":0,"homeRoadFlag":"R","opponentAbbrev":"SEA","pim":0,"plusMinus":0,"points":0,"powerPlayGoals":0,"shifts":8,"shorthandedGoals":0,"shots":0,"teamAbbrev":"TBL","toi":"4:15"},{"assists":0,"gameDate":"2023-11-30","gameId":2023020345,"gameTypeId":2,"goals":0,"homeRoadFlag":"H","opponentAbbrev":"PIT","pim":0,"plusMinus":-1,"points":0,"powerPlayGoals":0,"shifts":9,"shorthandedGoals":0,"shots":1,"teamAbbrev":"TBL","toi":"5:10"},{"assists":0,"gameDate":"2023-11-28","gameId":2023020334,"gameTypeId":2,"goals":0,"homeRoadFlag":"R","opponentAbbrev":"ARI","pim":0,"plusMinus":0,"points":0,"powerPlayGoals":0,"shifts":11,"shorthandedGoals":0,"shots":0,"teamAbbrev":"TBL","toi":"7:00"},{"assists":0,"gameDate":"2023-11-27","gameId":2023020324,"gameTypeId":2,"goals":0,"homeRoadFlag":"R","opponentAbbrev":"COL","pim":0,"plusMinus":0,"points":0,"powerPlayGoals":0,"shifts":14,"shorthandedGoals":0,"shots":4,"teamAbbrev":"TBL","toi":"9:30"}],"seasonTotals":[{"assists":11,"gameTypeId":2,"gamesPlayed":25,"goals":17,"leagueAbbrev":"USHS-MN","pim":12,"points":28,"season":20132014,"sequence":70932,"teamName":{"default":"Hermantown High"}},{"assists":2,"gameTypeId":3,"gamesPlayed":3,"goals":0,"leagueAbbrev":"USHS-MN","pim":0,"points":2,"season":20132014,"sequence":70932,"teamName":{"default":"Hermantown High"}},{"assists":19,"gameTypeId":2,"gamesPlayed":25,"goals":17,"leagueAbbrev":"USHS-MN","pim":12,"points":36,"season":20142015,"sequence":70932,"teamName":{"default":"Hermantown High"}},{"assists":4,"gameTypeId":2,"gamesPlayed":19,"goals":4,"leagueAbbrev":"UMHSEHL","pim":8,"points":8,"season":20142015,"sequence":97778,"teamName":{"default":"Team North"}},{"assists":3,"gameTypeId":3,"gamesPlayed":3,"goals":3,"leagueAbbrev":"USHS-MN","pim":0,"points":6,"season":20142015,"sequence":70932,"teamName":{"default":"Hermantown High"}},{"assists":1,"gameTypeId":3,"gamesPlayed":3,"goals":0,"leagueAbbrev":"UMHSEHL","pim":0,"points":1,"season":20142015,"sequence":97778,"teamName":{"default":"Team North"}},{"assists":1,"gameTypeId":3,"gamesPlayed":4,"goals":3,"leagueAbbrev":"USA-S16","points":4,"season":20142015,"sequence":10192984,"teamName":{"default":"Team Forest"}},{"assists":2,"gameTypeId":3,"gamesPlayed":3,"goals":3,"leagueAbbrev":"MNHP-16","points":5,"season":20142015,"sequence":10367878,"teamName":{"default":"B16 - Blue (Final 54)"}},{"assists":22,"gameTypeId":2,"gamesPlayed":24,"goals":31,"leagueAbbrev":"USHS-MN","pim":23,"points":53,"season":20152016,"sequence":70948,"teamName":{"default":"Hermantown High"}},{"assists":7,"gameTypeId":2,"gamesPlayed":20,"goals":7,"leagueAbbrev":"UMHSEHL","pim":4,"points":14,"season":20152016,"sequence":97808,"teamName":{"default":"Team Kowalski's"}},{"assists":1,"gameTypeId":2,"gamesPlayed":9,"goals":2,"leagueAbbrev":"NAHL","pim":4,"plusMinus":-8,"points":3,"season":20152016,"sequence":138174,"teamName":{"default":"Minnesota Wilderness"}},{"assists":0,"gameTypeId":3,"gamesPlayed":3,"goals":4,"leagueAbbrev":"USHS-MN","pim":0,"points":4,"season":20152016,"sequence":70948,"teamName":{"default":"Hermantown High"}},{"assists":1,"gameTypeId":3,"gamesPlayed":3,"goals":3,"leagueAbbrev":"UMHSEHL","pim":2,"points":4,"season":20152016,"sequence":97808,"teamName":{"default":"Team Kowalski's"}},{"assists":0,"gameTypeId":3,"gamesPlayed":8,"goals":0,"leagueAbbrev":"NAHL","pim":4,"plusMinus":-6,"points":0,"season":20152016,"sequence":138174,"teamName":{"default":"Minnesota Wilderness"}},{"assists":2,"gameTypeId":2,"gamesPlayed":22,"goals":3,"leagueAbbrev":"USHL","pim":19,"plusMinus":2,"points":5,"season":20162017,"sequence":9956,"teamName":{"default":"Sioux City Musketeers"}},{"assists":11,"gameTypeId":2,"gamesPlayed":60,"goals":28,"leagueAbbrev":"USHL","pim":34,"plusMinus":-13,"points":39,"season":20172018,"sequence":9956,"teamName":{"default":"Sioux City Musketeers"}},{"assists":12,"gameTypeId":2,"gamesPlayed":42,"goals":7,"leagueAbbrev":"NCAA","pim":14,"plusMinus":14,"points":19,"season":20182019,"sequence":18500,"teamName":{"default":"Univ. of Minnesota-Duluth"}},{"assists":17,"gameTypeId":2,"gamesPlayed":34,"goals":16,"leagueAbbrev":"NCAA","pim":16,"plusMinus":14,"points":33,"season":20192020,"sequence":18500,"teamName":{"default":"Univ. of Minnesota-Duluth"}},{"assists":1,"gameTypeId":2,"gamesPlayed":9,"goals":2,"leagueAbbrev":"AHL","pim":2,"plusMinus":5,"points":3,"season":20202021,"sequence":1057,"teamName":{"default":"Syracuse Crunch"}},{"assists":8,"gameTypeId":2,"gamesPlayed":28,"goals":15,"leagueAbbrev":"NCAA","pim":22,"plusMinus":3,"points":23,"season":20202021,"sequence":18500,"teamName":{"default":"Univ. of Minnesota-Duluth"}},{"assists":19,"gameTypeId":2,"gamesPlayed":69,"goals":20,"leagueAbbrev":"AHL","pim":55,"plusMinus":7,"points":39,"season":20212022,"sequence":1057,"teamName":{"default":"Syracuse Crunch"}},{"assists":1,"gameTypeId":3,"gamesPlayed":5,"goals":2,"leagueAbbrev":"AHL","pim":0,"plusMinus":4,"points":3,"season":20212022,"sequence":1057,"teamName":{"default":"Syracuse Crunch"}},{"assists":0,"avgToi":"9:06","faceoffWinningPctg":0.0,"gameTypeId":2,"gameWinningGoals":0,"gamesPlayed":17,"goals":1,"leagueAbbrev":"NHL","otGoals":0,"pim":2,"plusMinus":-5,"points":1,"powerPlayGoals":0,"powerPlayPoints":0,"season":20222023,"sequence":1,"shootingPctg":0.083333,"shorthandedGoals":0,"shorthandedPoints":0,"shots":12,"teamCommonName":{"default":"Lightning"},"teamName":{"default":"Tampa Bay Lightning","fr":"Lightning de Tampa Bay"},"teamPlaceNameWithPreposition":{"default":"Tampa Bay","fr":"de Tampa Bay"}},{"assists":12,"gameTypeId":2,"gamesPlayed":52,"goals":7,"leagueAbbrev":"AHL","pim":23,"plusMinus":-4,"points":19,"season":20222023,"sequence":1057,"teamName":{"default":"Syracuse Crunch"}},{"assists":3,"gameTypeId":3,"gamesPlayed":5,"goals":0,"leagueAbbrev":"AHL","pim":2,"plusMinus":-5,"points":3,"season":20222023,"sequence":1057,"teamName":{"default":"Syracuse Crunch"}},{"assists":2,"avgToi":"6:42","faceoffWinningPctg":0.0,"gameTypeId":2,"gameWinningGoals":0,"gamesPlayed":9,"goals":0,"leagueAbbrev":"NHL","otGoals":0,"pim":0,"plusMinus":0,"points":2,"powerPlayGoals":0,"powerPlayPoints":0,"season":20232024,"sequence":1,"shootingPctg":0.0,"shorthandedGoals":0,"shorthandedPoints":0,"shots":9,"teamCommonName":{"default":"Lightning"},"teamName":{"default":"Tampa Bay Lightning","fr":"Lightning de Tampa Bay"},"teamPlaceNameWithPreposition":{"default":"Tampa Bay","fr":"de Tampa Bay"}},{"assists":19,"gameTypeId":2,"gamesPlayed":53,"goals":20,"leagueAbbrev":"AHL","pim":14,"plusMinus":8,"points":39,"season":20232024,"sequence":1057,"teamName":{"default":"Syracuse Crunch"}},{"assists":0,"gameTypeId":3,"gamesPlayed":8,"goals":4,"leagueAbbrev":"AHL","pim":0,"plusMinus":-1,"points":4,"season":20232024,"sequence":1057,"teamName":{"default":"Syracuse Crunch"}}],"currentTeamRoster":[{"playerId":8484813,"lastName":{"default":"Bavaro"},"firstName":{"default":"Drew"},"playerSlug":"drew-bavaro-8484813"},{"playerId":8481556,"lastName":{"default":"Beecher"},"firstName":{"default":"John"},"playerSlug":"john-beecher-8481556"},{"playerId":8479638,"lastName":{"default":"Brazeau"},"firstName":{"default":"Justin"},"playerSlug":"justin-brazeau-8479638"},{"playerId":8477887,"lastName":{"default":"Brown"},"firstName":{"default":"Patrick"},"playerSlug":"patrick-brown-8477887"},{"playerId":8483017,"lastName":{"default":"Brunet"},"firstName":{"default":"Frederic"},"playerSlug":"frederic-brunet-8483017"},{"playerId":8483548,"lastName":{"default":"Bussi"},"firstName":{"default":"Brandon"},"playerSlug":"brandon-bussi-8483548"},{"playerId":8480828,"lastName":{"default":"Callahan"},"firstName":{"default":"Michael"},"playerSlug":"michael-callahan-8480828"},{"playerId":8478443,"lastName":{"default":"Carlo"},"firstName":{"default":"Brandon"},"playerSlug":"brandon-carlo-8478443"},{"playerId":8475745,"lastName":{"default":"Coyle"},"firstName":{"default":"Charlie"},"playerSlug":"charlie-coyle-8475745"},{"playerId":8480022,"lastName":{"default":"DiPietro","cs":"Dipietro","de":"Dipietro","es":"Dipietro","fi":"Dipietro","sk":"Dipietro","sv":"Dipietro"},"firstName":{"default":"Michael"},"playerSlug":"michael-dipietro-8480022"},{"playerId":8482213,"lastName":{"default":"Duran"},"firstName":{"default":"Riley"},"playerSlug":"riley-duran-8482213"},{"playerId":8483438,"lastName":{"default":"Edward"},"firstName":{"default":"Jackson"},"playerSlug":"jackson-edward-8483438"},{"playerId":8481558,"lastName":{"default":"Farinacci"},"firstName":{"default":"John"},"playerSlug":"john-farinacci-8481558"},{"playerId":8479365,"lastName":{"default":"Frederic"},"firstName":{"default":"Trent"},"playerSlug":"trent-frederic-8479365"},{"playerId":8479987,"lastName":{"default":"Geekie"},"firstName":{"default":"Morgan"},"playerSlug":"morgan-geekie-8479987"},{"playerId":8482739,"lastName":{"default":"Harrison"},"firstName":{"default":"Brett"},"playerSlug":"brett-harrison-8482739"},{"playerId":8479368,"lastName":{"default":"Jones"},"firstName":{"default":"Max"},"playerSlug":"max-jones-8479368"},{"playerId":8480355,"lastName":{"default":"Kastelic"},"firstName":{"default":"Mark"},"playerSlug":"mark-kastelic-8480355"},{"playerId":8481043,"lastName":{"default":"Koepke"},"firstName":{"default":"Cole"},"playerSlug":"cole-koepke-8481043"},{"playerId":8476914,"lastName":{"default":"Korpisalo"},"firstName":{"default":"Joonas"},"playerSlug":"joonas-korpisalo-8476914"},{"playerId":8482479,"lastName":{"default":"Kuntar"},"firstName":{"default":"Trevor"},"playerSlug":"trevor-kuntar-8482479"},{"playerId":8479968,"lastName":{"default":"Lettieri"},"firstName":{"default":"Vinni"},"playerSlug":"vinni-lettieri-8479968"},{"playerId":8477496,"lastName":{"default":"Lindholm"},"firstName":{"default":"Elias"},"playerSlug":"elias-lindholm-8477496"},{"playerId":8476854,"lastName":{"default":"Lindholm"},"firstName":{"default":"Hampus"},"playerSlug":"hampus-lindholm-8476854"},{"playerId":8482511,"lastName":{"default":"Lohrei"},"firstName":{"default":"Mason"},"playerSlug":"mason-lohrei-8482511"},{"playerId":8482763,"lastName":{"default":"Lysell"},"firstName":{"default":"Fabian"},"playerSlug":"fabian-lysell-8482763"},{"playerId":8473419,"lastName":{"default":"Marchand"},"firstName":{"default":"Brad"},"playerSlug":"brad-marchand-8473419"},{"playerId":8482893,"lastName":{"default":"Mast"},"firstName":{"default":"Ryan"},"playerSlug":"ryan-mast-8482893"},{"playerId":8479325,"lastName":{"default":"McAvoy"},"firstName":{"default":"Charlie"},"playerSlug":"charlie-mcavoy-8479325"},{"playerId":8483397,"lastName":{"default":"McLaughlin"},"firstName":{"default":"Marc"},"playerSlug":"marc-mclaughlin-8483397"},{"playerId":8483567,"lastName":{"default":"Merkulov"},"firstName":{"default":"Georgii"},"playerSlug":"georgii-merkulov-8483567"},{"playerId":8480070,"lastName":{"default":"Mitchell"},"firstName":{"default":"Ian"},"playerSlug":"ian-mitchell-8480070"},{"playerId":8484899,"lastName":{"default":"Nelson"},"firstName":{"default":"Jaxon"},"playerSlug":"jaxon-nelson-8484899"},{"playerId":8477851,"lastName":{"default":"Oesterle"},"firstName":{"default":"Jordan"},"playerSlug":"jordan-oesterle-8477851"},{"playerId":8477956,"lastName":{"default":"Pastrnak","cs":"Pastrňák","sk":"Pastrňák"},"firstName":{"default":"David"},"playerSlug":"david-pastrnak-8477956"},{"playerId":8479369,"lastName":{"default":"Peeke"},"firstName":{"default":"Andrew"},"playerSlug":"andrew-peeke-8479369"},{"playerId":8483505,"lastName":{"default":"Poitras"},"firstName":{"default":"Matthew"},"playerSlug":"matthew-poitras-8483505"},{"playerId":8480831,"lastName":{"default":"Regula"},"firstName":{"default":"Alec"},"playerSlug":"alec-regula-8480831"},{"playerId":8482399,"lastName":{"default":"Sweezey"},"firstName":{"default":"Billy"},"playerSlug":"billy-sweezey-8482399"},{"playerId":8479705,"lastName":{"default":"Viel"},"firstName":{"default":"Jeffrey"},"playerSlug":"jeffrey-viel-8479705"},{"playerId":8479362,"lastName":{"default":"Tufte"},"firstName":{"default":"Riley"},"playerSlug":"riley-tufte-8479362"},{"playerId":8478450,"lastName":{"default":"Wotherspoon"},"firstName":{"default":"Parker"},"playerSlug":"parker-wotherspoon-8478450"},{"playerId":8478401,"lastName":{"default":"Zacha"},"firstName":{"default":"Pavel"},"playerSlug":"pavel-zacha-8478401"},{"playerId":8477507,"lastName":{"default":"Zadorov"},"firstName":{"default":"Nikita"},"playerSlug":"nikita-zadorov-8477507"}]}