{"playerId":8481441,"isActive":true,"currentTeamId":17,"currentTeamAbbrev":"DET","fullTeamName":{"default":"Detroit Red Wings","fr":"Red Wings de Detroit"},"teamCommonName":{"default":"Red Wings"},"teamPlaceNameWithPreposition":{"default":"Detroit","fr":"de Detroit"},"firstName":{"default":"Joe"},"lastName":{"default":"Snively"},"teamLogo":"https://assets.nhle.com/logos/nhl/svg/DET_light.svg","sweaterNumber":21,"position":"C","headshot":"https://assets.nhle.com/mugs/nhl/20242025/DET/8481441.png","heroImage":"https://assets.nhle.com/mugs/actionshots/1296x729/8481441.jpg","heightInInches":69,"heightInCentimeters":175,"weightInPounds":176,"weightInKilograms":80,"birthDate":"1996-01-01","birthCity":{"default":"Herndon"},"birthStateProvince":{"default":"Virginia","fr":"Virginie"},"birthCountry":"USA","shootsCatches":"L","playerSlug":"joe-snively-8481441","inTop100AllTime":0,"inHHOF":0,"featuredStats":{"season":20232024,"regularSeason":{"subSeason":{"assists":0,"gameWinningGoals":0,"gamesPlayed":3,"goals":0,"otGoals":0,"pim":0,"plusMinus":-1,"points":0,"powerPlayGoals":0,"powerPlayPoints":0,"shootingPctg":0.0,"shorthandedGoals":0,"shorthandedPoints":0,"shots":0},"career":{"assists":5,"gameWinningGoals":0,"gamesPlayed":27,"goals":6,"otGoals":0,"pim":2,"plusMinus":5,"points":11,"powerPlayGoals":1,"powerPlayPoints":1,"shootingPctg":0.16210000000000002,"shorthandedGoals":0,"shorthandedPoints":0,"shots":37}}},"careerTotals":{"regularSeason":{"assists":5,"avgToi":"11:40","faceoffWinningPctg":0.5,"gameWinningGoals":0,"gamesPlayed":27,"goals":6,"otGoals":0,"pim":2,"plusMinus":5,"points":11,"powerPlayGoals":1,"powerPlayPoints":1,"shootingPctg":0.16210000000000002,"shorthandedGoals":0,"shorthandedPoints":0,"shots":37}},"shopLink":"#TODO","twitterLink":"#TODO","watchLink":"#TODO","last5Games":[{"assists":0,"gameDate":"2023-12-17","gameId":2023020475,"gameTypeId":2,"goals":0,"homeRoadFlag":"R","opponentAbbrev":"CAR","pim":0,"plusMinus":-1,"points":0,"powerPlayGoals":0,"shifts":7,"shorthandedGoals":0,"shots":0,"teamAbbrev":"WSH","toi":"5:43"},{"assists":0,"gameDate":"2023-12-16","gameId":2023020468,"gameTypeId":2,"goals":0,"homeRoadFlag":"R","opponentAbbrev":"NSH","pim":0,"plusMinus":0,"points":0,"powerPlayGoals":0,"shifts":15,"shorthandedGoals":0,"shots":0,"teamAbbrev":"WSH","toi":"12:48"},{"assists":0,"gameDate":"2023-12-14","gameId":2023020448,"gameTypeId":2,"goals":0,"homeRoadFlag":"R","opponentAbbrev":"PHI","pim":0,"plusMinus":0,"points":0,"powerPlayGoals":0,"shifts":10,"shorthandedGoals":0,"shots":0,"teamAbbrev":"WSH","toi":"6:31"}],"seasonTotals":[{"assists":0,"gameTypeId":2,"gamesPlayed":2,"goals":0,"leagueAbbrev":"QC Int PW","pim":0,"points":0,"season":20082009,"sequence":278312,"teamName":{"default":"Washington Little Caps PW"}},{"assists":19,"gameTypeId":2,"gamesPlayed":28,"goals":22,"leagueAbbrev":"AYHL 13U","pim":16,"points":41,"season":20092010,"sequence":222359,"teamName":{"default":"Washington Little Caps 13U AAA"}},{"assists":4,"gameTypeId":2,"gamesPlayed":7,"goals":6,"leagueAbbrev":"WSI U15","pim":4,"points":10,"season":20112012,"sequence":260380,"teamName":{"default":"Selects Academy 15U"}},{"assists":4,"gameTypeId":3,"gamesPlayed":7,"goals":6,"leagueAbbrev":"WSI U15","pim":4,"points":10,"season":20112012,"sequence":260149,"teamName":{"default":"Selects Hockey Academy U15"}},{"assists":7,"gameTypeId":2,"gamesPlayed":48,"goals":9,"leagueAbbrev":"USHL","pim":10,"plusMinus":-7,"points":16,"season":20122013,"sequence":9108,"teamName":{"default":"Sioux City Musketeers"}},{"assists":31,"gameTypeId":2,"gamesPlayed":56,"goals":14,"leagueAbbrev":"USHL","pim":45,"plusMinus":9,"points":45,"season":20132014,"sequence":9108,"teamName":{"default":"Sioux City Musketeers"}},{"assists":4,"gameTypeId":3,"gamesPlayed":8,"goals":0,"leagueAbbrev":"USHL","pim":4,"plusMinus":0,"points":4,"season":20132014,"sequence":9108,"teamName":{"default":"Sioux City Musketeers"}},{"assists":1,"gameTypeId":3,"gamesPlayed":5,"goals":1,"leagueAbbrev":"Hlinka Gretzky Cup","pim":4,"plusMinus":-1,"points":2,"season":20132014,"sequence":140404,"teamName":{"default":"USA U18"}},{"assists":37,"gameTypeId":2,"gamesPlayed":55,"goals":27,"leagueAbbrev":"USHL","pim":26,"plusMinus":12,"points":64,"season":20142015,"sequence":9108,"teamName":{"default":"Sioux City Musketeers"}},{"assists":3,"gameTypeId":3,"gamesPlayed":5,"goals":1,"leagueAbbrev":"USHL","pim":8,"plusMinus":-6,"points":4,"season":20142015,"sequence":9108,"teamName":{"default":"Sioux City Musketeers"}},{"assists":1,"gameTypeId":3,"gamesPlayed":4,"goals":2,"leagueAbbrev":"WJAC-19","pim":6,"points":3,"season":20142015,"sequence":86845,"teamName":{"default":"USA U19"}},{"assists":18,"gameTypeId":2,"gamesPlayed":32,"goals":10,"leagueAbbrev":"NCAA","pim":12,"plusMinus":5,"points":28,"season":20152016,"sequence":8420,"teamName":{"default":"Yale Univ."}},{"assists":25,"gameTypeId":2,"gamesPlayed":33,"goals":14,"leagueAbbrev":"NCAA","pim":34,"plusMinus":-3,"points":39,"season":20162017,"sequence":8420,"teamName":{"default":"Yale Univ."}},{"assists":17,"gameTypeId":2,"gamesPlayed":31,"goals":19,"leagueAbbrev":"NCAA","pim":18,"plusMinus":11,"points":36,"season":20172018,"sequence":8420,"teamName":{"default":"Yale Univ."}},{"assists":5,"gameTypeId":2,"gamesPlayed":9,"goals":2,"leagueAbbrev":"AHL","pim":0,"plusMinus":3,"points":7,"season":20182019,"sequence":997,"teamName":{"default":"Hershey Bears"}},{"assists":21,"gameTypeId":2,"gamesPlayed":33,"goals":15,"leagueAbbrev":"NCAA","pim":17,"plusMinus":5,"points":36,"season":20182019,"sequence":8420,"teamName":{"default":"Yale Univ."}},{"assists":0,"gameTypeId":3,"gamesPlayed":2,"goals":0,"leagueAbbrev":"AHL","pim":0,"plusMinus":0,"points":0,"season":20182019,"sequence":997,"teamName":{"default":"Hershey Bears"}},{"assists":12,"gameTypeId":2,"gamesPlayed":45,"goals":12,"leagueAbbrev":"AHL","pim":14,"plusMinus":7,"points":24,"season":20192020,"sequence":997,"teamName":{"default":"Hershey Bears"}},{"assists":11,"gameTypeId":2,"gamesPlayed":30,"goals":6,"leagueAbbrev":"AHL","pim":8,"plusMinus":7,"points":17,"season":20202021,"sequence":997,"teamName":{"default":"Hershey Bears"}},{"assists":3,"avgToi":"11:33","faceoffWinningPctg":0.0,"gameTypeId":2,"gameWinningGoals":0,"gamesPlayed":12,"goals":4,"leagueAbbrev":"NHL","otGoals":0,"pim":2,"plusMinus":3,"points":7,"powerPlayGoals":1,"powerPlayPoints":1,"season":20212022,"sequence":1,"shootingPctg":0.19,"shorthandedGoals":0,"shorthandedPoints":0,"shots":21,"teamCommonName":{"default":"Capitals"},"teamName":{"default":"Washington Capitals","fr":"Capitals de Washington"},"teamPlaceNameWithPreposition":{"default":"Washington","fr":"de Washington"}},{"assists":23,"gameTypeId":2,"gamesPlayed":35,"goals":15,"leagueAbbrev":"AHL","pim":18,"plusMinus":22,"points":38,"season":20212022,"sequence":997,"teamName":{"default":"Hershey Bears"}},{"assists":0,"gameTypeId":3,"gamesPlayed":1,"goals":0,"leagueAbbrev":"AHL","pim":0,"plusMinus":0,"points":0,"season":20212022,"sequence":997,"teamName":{"default":"Hershey Bears"}},{"assists":2,"avgToi":"12:36","faceoffWinningPctg":0.666667,"gameTypeId":2,"gameWinningGoals":0,"gamesPlayed":12,"goals":2,"leagueAbbrev":"NHL","otGoals":0,"pim":0,"plusMinus":3,"points":4,"powerPlayGoals":0,"powerPlayPoints":0,"season":20222023,"sequence":1,"shootingPctg":0.125,"shorthandedGoals":0,"shorthandedPoints":0,"shots":16,"teamCommonName":{"default":"Capitals"},"teamName":{"default":"Washington Capitals","fr":"Capitals de Washington"},"teamPlaceNameWithPreposition":{"default":"Washington","fr":"de Washington"}},{"assists":18,"gameTypeId":2,"gamesPlayed":32,"goals":9,"leagueAbbrev":"AHL","pim":6,"plusMinus":10,"points":27,"season":20222023,"sequence":997,"teamName":{"default":"Hershey Bears"}},{"assists":13,"gameTypeId":3,"gamesPlayed":20,"goals":2,"leagueAbbrev":"AHL","pim":6,"plusMinus":2,"points":15,"season":20222023,"sequence":997,"teamName":{"default":"Hershey Bears"}},{"assists":0,"avgToi":"8:21","faceoffWinningPctg":0.0,"gameTypeId":2,"gameWinningGoals":0,"gamesPlayed":3,"goals":0,"leagueAbbrev":"NHL","otGoals":0,"pim":0,"plusMinus":-1,"points":0,"powerPlayGoals":0,"powerPlayPoints":0,"season":20232024,"sequence":1,"shootingPctg":0.0,"shorthandedGoals":0,"shorthandedPoints":0,"shots":0,"teamCommonName":{"default":"Capitals"},"teamName":{"default":"Washington Capitals","fr":"Capitals de Washington"},"teamPlaceNameWithPreposition":{"default":"Washington","fr":"de Washington"}},{"assists":45,"gameTypeId":2,"gamesPlayed":69,"goals":14,"leagueAbbrev":"AHL","pim":26,"plusMinus":8,"points":59,"season":20232024,"sequence":997,"teamName":{"default":"Hershey Bears"}},{"assists":14,"gameTypeId":3,"gamesPlayed":20,"goals":4,"leagueAbbrev":"AHL","pim":26,"plusMinus":0,"points":18,"season":20232024,"sequence":997,"teamName":{"default":"Hershey Bears"}},{"assists":4,"gameTypeId":2,"gamesPlayed":7,"goals":1,"leagueAbbrev":"AHL","pim":2,"plusMinus":2,"points":5,"season":20242025,"sequence":987,"teamName":{"default":"Grand Rapids Griffins"}}],"currentTeamRoster":[{"playerId":8481013,"lastName":{"default":"Berggren"},"firstName":{"default":"Jonatan"},"playerSlug":"jonatan-berggren-8481013"},{"playerId":8475279,"lastName":{"default":"Chiarot"},"firstName":{"default":"Ben"},"playerSlug":"ben-chiarot-8475279"},{"playerId":8477456,"lastName":{"default":"Compher"},"firstName":{"default":"J.T."},"playerSlug":"j-t-compher-8477456"},{"playerId":8477429,"lastName":{"default":"Copp"},"firstName":{"default":"Andrew"},"playerSlug":"andrew-copp-8477429"},{"playerId":8479337,"lastName":{"default":"DeBrincat"},"firstName":{"default":"Alex"},"playerSlug":"alex-debrincat-8479337"},{"playerId":8482762,"lastName":{"default":"Edvinsson"},"firstName":{"default":"Simon"},"playerSlug":"simon-edvinsson-8482762"},{"playerId":8478432,"lastName":{"default":"Fischer"},"firstName":{"default":"Christian"},"playerSlug":"christian-fischer-8478432"},{"playerId":8476979,"lastName":{"default":"Gustafsson"},"firstName":{"default":"Erik"},"playerSlug":"erik-gustafsson-8476979"},{"playerId":8481607,"lastName":{"default":"Johansson"},"firstName":{"default":"Albert"},"playerSlug":"albert-johansson-8481607"},{"playerId":8474141,"lastName":{"default":"Kane"},"firstName":{"default":"Patrick"},"playerSlug":"patrick-kane-8474141"},{"playerId":8477946,"lastName":{"default":"Larkin"},"firstName":{"default":"Dylan"},"playerSlug":"dylan-larkin-8477946"},{"playerId":8479312,"lastName":{"default":"Lyon"},"firstName":{"default":"Alex"},"playerSlug":"alex-lyon-8479312"},{"playerId":8476874,"lastName":{"default":"Maatta","cs":"Määttä","fi":"Määttä","sk":"Määttä"},"firstName":{"default":"Olli"},"playerSlug":"olli-maatta-8476874"},{"playerId":8477353,"lastName":{"default":"Motte"},"firstName":{"default":"Tyler"},"playerSlug":"tyler-motte-8477353"},{"playerId":8473507,"lastName":{"default":"Petry"},"firstName":{"default":"Jeff"},"playerSlug":"jeff-petry-8473507"},{"playerId":8479992,"lastName":{"default":"Rasmussen"},"firstName":{"default":"Michael"},"playerSlug":"michael-rasmussen-8479992"},{"playerId":8482078,"lastName":{"default":"Raymond"},"firstName":{"default":"Lucas"},"playerSlug":"lucas-raymond-8482078"},{"playerId":8481542,"lastName":{"default":"Seider"},"firstName":{"default":"Moritz"},"playerSlug":"moritz-seider-8481542"},{"playerId":8475660,"lastName":{"default":"Talbot"},"firstName":{"default":"Cam"},"playerSlug":"cam-talbot-8475660"},{"playerId":8475765,"lastName":{"default":"Tarasenko"},"firstName":{"default":"Vladimir"},"playerSlug":"vladimir-tarasenko-8475765"},{"playerId":8480813,"lastName":{"default":"Veleno"},"firstName":{"default":"Joe","cs":"Joseph","de":"Joseph","es":"Joseph","fi":"Joseph","sk":"Joseph","sv":"Joseph"},"playerSlug":"joe-veleno-8480813"}]}