{
  "copyright" : "NHL and the NHL Shield are registered trademarks of the National Hockey League. NHL and NHL team marks are the property of the NHL and its teams. © NHL 2023. All Rights Reserved.",
  "stats" : [ {
    "type" : {
      "displayName" : "yearByYear",
      "gameType" : null
    },
    "splits" : [ {
      "season" : "20142015",
      "stat" : {
        "assists" : 14,
        "goals" : 6,
        "pim" : 55,
        "games" : 27,
        "penaltyMinutes" : "55",
        "points" : 20
      },
      "team" : {
        "name" : "Prince Albert Raiders U15 AA",
        "link" : "/api/v1/teams/null"
      },
      "league" : {
        "name" : "SAAHL U15",
        "link" : "/api/v1/league/null"
      },
      "sequenceNumber" : 129206
    }, {
      "season" : "20152016",
      "stat" : {
        "assists" : 1,
        "goals" : 0,
        "pim" : 0,
        "games" : 2,
        "penaltyMinutes" : "0",
        "points" : 1
      },
      "team" : {
        "name" : "Prince Albert Mintos U18 AAA",
        "link" : "/api/v1/teams/null"
      },
      "league" : {
        "name" : "SMAAAHL",
        "link" : "/api/v1/league/null"
      },
      "sequenceNumber" : 43334
    }, {
      "season" : "20152016",
      "stat" : {
        "assists" : 13,
        "goals" : 7,
        "pim" : 26,
        "games" : 30,
        "penaltyMinutes" : "26",
        "points" : 20
      },
      "team" : {
        "name" : "Prince Albert Raiders U15 AA",
        "link" : "/api/v1/teams/null"
      },
      "league" : {
        "name" : "SAAHL U15",
        "link" : "/api/v1/league/null"
      },
      "sequenceNumber" : 129206
    }, {
      "season" : "20162017",
      "stat" : {
        "assists" : 0,
        "goals" : 0,
        "pim" : 0,
        "games" : 1,
        "penaltyMinutes" : "0",
        "plusMinus" : 0,
        "points" : 0
      },
      "team" : {
        "name" : "Brandon Wheat Kings",
        "link" : "/api/v1/teams/null"
      },
      "league" : {
        "name" : "WHL",
        "link" : "/api/v1/league/null"
      },
      "sequenceNumber" : 9591
    }, {
      "season" : "20162017",
      "stat" : {
        "assists" : 19,
        "goals" : 12,
        "pim" : 73,
        "games" : 35,
        "penaltyMinutes" : "73",
        "points" : 31
      },
      "team" : {
        "name" : "Prince Albert Mintos U18 AAA",
        "link" : "/api/v1/teams/null"
      },
      "league" : {
        "name" : "SMAAAHL",
        "link" : "/api/v1/league/null"
      },
      "sequenceNumber" : 43334
    }, {
      "season" : "20172018",
      "stat" : {
        "assists" : 21,
        "goals" : 1,
        "pim" : 16,
        "games" : 66,
        "penaltyMinutes" : "16",
        "plusMinus" : 10,
        "points" : 22
      },
      "team" : {
        "name" : "Brandon Wheat Kings",
        "link" : "/api/v1/teams/null"
      },
      "league" : {
        "name" : "WHL",
        "link" : "/api/v1/league/null"
      },
      "sequenceNumber" : 9591
    }, {
      "season" : "20172018",
      "stat" : {
        "assists" : 1,
        "goals" : 1,
        "pim" : 0,
        "games" : 6,
        "penaltyMinutes" : "0",
        "points" : 2
      },
      "team" : {
        "name" : "Canada White U17",
        "link" : "/api/v1/teams/null"
      },
      "league" : {
        "name" : "WHC-17",
        "link" : "/api/v1/league/null"
      },
      "sequenceNumber" : 163790
    }, {
      "season" : "20172018",
      "stat" : {
        "assists" : 1,
        "goals" : 0,
        "pim" : 0,
        "games" : 3,
        "penaltyMinutes" : "0",
        "points" : 1
      },
      "team" : {
        "name" : "Team Gold",
        "link" : "/api/v1/teams/null"
      },
      "league" : {
        "name" : "U17-Dev",
        "link" : "/api/v1/league/null"
      },
      "sequenceNumber" : 178249
    }, {
      "season" : "20182019",
      "stat" : {
        "assists" : 16,
        "goals" : 8,
        "pim" : 26,
        "games" : 58,
        "penaltyMinutes" : "26",
        "plusMinus" : 13,
        "points" : 24
      },
      "team" : {
        "name" : "Brandon Wheat Kings",
        "link" : "/api/v1/teams/null"
      },
      "league" : {
        "name" : "WHL",
        "link" : "/api/v1/league/null"
      },
      "sequenceNumber" : 9591
    }, {
      "season" : "20182019",
      "stat" : {
        "assists" : 1,
        "goals" : 2,
        "pim" : 2,
        "games" : 7,
        "penaltyMinutes" : "2",
        "plusMinus" : 9,
        "points" : 3
      },
      "team" : {
        "name" : "Canada U18",
        "link" : "/api/v1/teams/null"
      },
      "league" : {
        "name" : "WJC-18",
        "link" : "/api/v1/league/null"
      },
      "sequenceNumber" : 17193
    }, {
      "season" : "20182019",
      "stat" : {
        "assists" : 0,
        "goals" : 0,
        "pim" : 4,
        "games" : 5,
        "penaltyMinutes" : "4",
        "points" : 0
      },
      "team" : {
        "name" : "Canada U18",
        "link" : "/api/v1/teams/null"
      },
      "league" : {
        "name" : "Hlinka Gretzky Cup",
        "link" : "/api/v1/league/null"
      },
      "sequenceNumber" : 144760
    }, {
      "season" : "20192020",
      "stat" : {
        "assists" : 35,
        "goals" : 7,
        "pim" : 42,
        "games" : 60,
        "penaltyMinutes" : "42",
        "plusMinus" : 9,
        "points" : 42
      },
      "team" : {
        "name" : "Brandon Wheat Kings",
        "link" : "/api/v1/teams/null"
      },
      "league" : {
        "name" : "WHL",
        "link" : "/api/v1/league/null"
      },
      "sequenceNumber" : 9591
    }, {
      "season" : "20202021",
      "stat" : {
        "assists" : 1,
        "goals" : 0,
        "pim" : 0,
        "games" : 2,
        "penaltyMinutes" : "0",
        "plusMinus" : 2,
        "points" : 1
      },
      "team" : {
        "name" : "Hartford Wolf Pack",
        "link" : "/api/v1/teams/null"
      },
      "league" : {
        "name" : "AHL",
        "link" : "/api/v1/league/null"
      },
      "sequenceNumber" : 847
    }, {
      "season" : "20202021",
      "stat" : {
        "assists" : 22,
        "goals" : 5,
        "pim" : 12,
        "games" : 22,
        "penaltyMinutes" : "12",
        "plusMinus" : 18,
        "points" : 27
      },
      "team" : {
        "name" : "Brandon Wheat Kings",
        "link" : "/api/v1/teams/null"
      },
      "league" : {
        "name" : "WHL",
        "link" : "/api/v1/league/null"
      },
      "sequenceNumber" : 9591
    }, {
      "season" : "20202021",
      "stat" : {
        "assists" : 1,
        "goals" : 0,
        "pim" : 0,
        "games" : 9,
        "penaltyMinutes" : "0",
        "plusMinus" : 2,
        "points" : 1
      },
      "team" : {
        "name" : "Canada",
        "link" : "/api/v1/teams/null"
      },
      "league" : {
        "name" : "WC",
        "link" : "/api/v1/league/null"
      },
      "sequenceNumber" : 17155
    }, {
      "season" : "20202021",
      "stat" : {
        "assists" : 2,
        "goals" : 1,
        "pim" : 25,
        "games" : 6,
        "penaltyMinutes" : "25",
        "plusMinus" : 8,
        "points" : 3
      },
      "team" : {
        "name" : "Canada U20",
        "link" : "/api/v1/teams/null"
      },
      "league" : {
        "name" : "WJC-20",
        "link" : "/api/v1/league/null"
      },
      "sequenceNumber" : 17216
    }, {
      "season" : "20212022",
      "stat" : {
        "timeOnIce" : "665:29",
        "assists" : 9,
        "goals" : 2,
        "pim" : 9,
        "shots" : 25,
        "games" : 43,
        "hits" : 60,
        "powerPlayGoals" : 0,
        "powerPlayPoints" : 1,
        "powerPlayTimeOnIce" : "03:43",
        "evenTimeOnIce" : "639:57",
        "penaltyMinutes" : "9",
        "faceOffPct" : 0.0,
        "shotPct" : 8.0,
        "gameWinningGoals" : 0,
        "overTimeGoals" : 0,
        "shortHandedGoals" : 0,
        "shortHandedPoints" : 0,
        "shortHandedTimeOnIce" : "21:49",
        "blocked" : 52,
        "plusMinus" : 5,
        "points" : 11,
        "shifts" : 840
      },
      "team" : {
        "id" : 3,
        "name" : "New York Rangers",
        "link" : "/api/v1/teams/3"
      },
      "league" : {
        "id" : 133,
        "name" : "National Hockey League",
        "link" : "/api/v1/league/133"
      },
      "sequenceNumber" : 1
    }, {
      "season" : "20212022",
      "stat" : {
        "assists" : 9,
        "goals" : 0,
        "pim" : 10,
        "games" : 24,
        "penaltyMinutes" : "10",
        "plusMinus" : 6,
        "points" : 9
      },
      "team" : {
        "name" : "Hartford Wolf Pack",
        "link" : "/api/v1/teams/null"
      },
      "league" : {
        "name" : "AHL",
        "link" : "/api/v1/league/null"
      },
      "sequenceNumber" : 847
    }, {
      "season" : "20222023",
      "stat" : {
        "timeOnIce" : "1273:27",
        "assists" : 13,
        "goals" : 5,
        "pim" : 16,
        "shots" : 79,
        "games" : 81,
        "hits" : 147,
        "powerPlayGoals" : 0,
        "powerPlayPoints" : 0,
        "powerPlayTimeOnIce" : "04:16",
        "evenTimeOnIce" : "1212:09",
        "penaltyMinutes" : "16",
        "faceOffPct" : 0.0,
        "shotPct" : 6.33,
        "gameWinningGoals" : 1,
        "overTimeGoals" : 0,
        "shortHandedGoals" : 0,
        "shortHandedPoints" : 0,
        "shortHandedTimeOnIce" : "57:02",
        "blocked" : 130,
        "plusMinus" : 9,
        "points" : 18,
        "shifts" : 1583
      },
      "team" : {
        "id" : 3,
        "name" : "New York Rangers",
        "link" : "/api/v1/teams/3"
      },
      "league" : {
        "id" : 133,
        "name" : "National Hockey League",
        "link" : "/api/v1/league/133"
      },
      "sequenceNumber" : 1
    }, {
      "season" : "20232024",
      "stat" : {
        "timeOnIce" : "140:04",
        "assists" : 1,
        "goals" : 1,
        "pim" : 2,
        "shots" : 10,
        "games" : 9,
        "hits" : 13,
        "powerPlayGoals" : 0,
        "powerPlayPoints" : 0,
        "powerPlayTimeOnIce" : "00:22",
        "evenTimeOnIce" : "132:35",
        "penaltyMinutes" : "2",
        "faceOffPct" : 0.0,
        "shotPct" : 10.0,
        "gameWinningGoals" : 0,
        "overTimeGoals" : 0,
        "shortHandedGoals" : 0,
        "shortHandedPoints" : 0,
        "shortHandedTimeOnIce" : "07:07",
        "blocked" : 15,
        "plusMinus" : -1,
        "points" : 2,
        "shifts" : 173
      },
      "team" : {
        "id" : 3,
        "name" : "New York Rangers",
        "link" : "/api/v1/teams/3"
      },
      "league" : {
        "id" : 133,
        "name" : "National Hockey League",
        "link" : "/api/v1/league/133"
      },
      "sequenceNumber" : 1
    } ]
  } ]
}