{"playerId":8482113,"isActive":true,"currentTeamId":13,"currentTeamAbbrev":"FLA","fullTeamName":{"default":"Florida Panthers","fr":"Panthers de la Floride"},"firstName":{"default":"Anton"},"lastName":{"default":"Lundell"},"teamLogo":"https://assets.nhle.com/logos/nhl/svg/FLA_light.svg","sweaterNumber":15,"position":"C","headshot":"https://assets.nhle.com/mugs/nhl/20232024/FLA/8482113.png","heroImage":"https://assets.nhle.com/mugs/actionshots/1296x729/8482113.jpg","heightInInches":73,"heightInCentimeters":185,"weightInPounds":190,"weightInKilograms":86,"birthDate":"2001-10-03","birthCity":{"default":"Espoo","sv":"Esbo"},"birthCountry":"FIN","shootsCatches":"L","draftDetails":{"year":2020,"teamAbbrev":"FLA","round":1,"pickInRound":12,"overallPick":12},"playerSlug":"anton-lundell-8482113","inTop100AllTime":0,"inHHOF":0,"featuredStats":{"season":20232024,"regularSeason":{"subSeason":{"gamesPlayed":30,"goals":2,"assists":10,"points":12,"plusMinus":3,"pim":12,"gameWinningGoals":0,"otGoals":0,"shots":58,"shootingPctg":0.034483,"powerPlayGoals":0,"powerPlayPoints":2,"shorthandedGoals":0,"shorthandedPoints":0},"career":{"gamesPlayed":167,"goals":32,"assists":57,"points":89,"plusMinus":37,"pim":73,"gameWinningGoals":5,"otGoals":0,"shots":332,"shootingPctg":0.09630000000000001,"powerPlayGoals":1,"powerPlayPoints":11,"shorthandedGoals":3,"shorthandedPoints":6}}},"careerTotals":{"regularSeason":{"gamesPlayed":167,"goals":32,"assists":57,"pim":73,"points":89,"plusMinus":37,"powerPlayGoals":1,"powerPlayPoints":11,"shorthandedPoints":6,"gameWinningGoals":5,"otGoals":0,"shots":332,"shootingPctg":0.09630000000000001,"faceoffWinningPctg":0.46509999999999996,"avgToi":"15:58","shorthandedGoals":3},"playoffs":{"gamesPlayed":30,"goals":3,"assists":8,"pim":4,"points":11,"plusMinus":2,"powerPlayGoals":0,"powerPlayPoints":2,"shorthandedPoints":1,"gameWinningGoals":0,"otGoals":0,"shots":47,"shootingPctg":0.0638,"faceoffWinningPctg":0.475,"avgToi":"16:06","shorthandedGoals":0}},"shopLink":"#TODO","twitterLink":"#TODO","watchLink":"#TODO","last5Games":[{"gameId":2023020530,"gameTypeId":2,"teamAbbrev":"FLA","homeRoadFlag":"R","gameDate":"2023-12-27","goals":0,"assists":0,"points":0,"plusMinus":0,"powerPlayGoals":0,"shots":3,"shifts":20,"shorthandedGoals":0,"pim":0,"opponentAbbrev":"TBL","toi":"14:13"},{"gameId":2023020514,"gameTypeId":2,"teamAbbrev":"FLA","homeRoadFlag":"H","gameDate":"2023-12-23","goals":0,"assists":0,"points":0,"plusMinus":-1,"powerPlayGoals":0,"shots":0,"shifts":15,"shorthandedGoals":0,"pim":0,"opponentAbbrev":"VGK","toi":"12:02"},{"gameId":2023020438,"gameTypeId":2,"teamAbbrev":"FLA","homeRoadFlag":"R","gameDate":"2023-12-12","goals":0,"assists":0,"points":0,"plusMinus":0,"powerPlayGoals":0,"shots":0,"shifts":20,"shorthandedGoals":0,"pim":0,"opponentAbbrev":"SEA","toi":"13:22"},{"gameId":2023020420,"gameTypeId":2,"teamAbbrev":"FLA","homeRoadFlag":"R","gameDate":"2023-12-10","goals":0,"assists":0,"points":0,"plusMinus":1,"powerPlayGoals":0,"shots":1,"shifts":17,"shorthandedGoals":0,"pim":0,"opponentAbbrev":"CBJ","toi":"14:59"},{"gameId":2023020406,"gameTypeId":2,"teamAbbrev":"FLA","homeRoadFlag":"H","gameDate":"2023-12-08","goals":0,"assists":2,"points":2,"plusMinus":3,"powerPlayGoals":0,"shots":5,"shifts":21,"shorthandedGoals":0,"pim":2,"opponentAbbrev":"PIT","toi":"16:35"}],"seasonTotals":[{"season":20152016,"gameTypeId":2,"leagueAbbrev":"U16 SM-sarja","teamName":{"default":"HIFK U16"},"sequence":81243,"gamesPlayed":27,"goals":4,"assists":11,"points":15,"pim":10},{"season":20152016,"gameTypeId":3,"leagueAbbrev":"U16 SM-sarja","teamName":{"default":"HIFK U16"},"sequence":81243,"gamesPlayed":5,"goals":1,"assists":0,"points":1,"pim":0},{"season":20162017,"gameTypeId":2,"leagueAbbrev":"U18 SM-sarja","teamName":{"default":"HIFK U18"},"sequence":25371,"gamesPlayed":29,"goals":3,"assists":12,"points":15,"pim":10},{"season":20162017,"gameTypeId":3,"leagueAbbrev":"U18 SM-sarja","teamName":{"default":"HIFK U18"},"sequence":25371,"gamesPlayed":2,"goals":1,"assists":1,"points":2,"pim":0},{"season":20162017,"gameTypeId":3,"leagueAbbrev":"U16 SM-sarja","teamName":{"default":"HIFK U16"},"sequence":81243,"gamesPlayed":3,"goals":3,"assists":4,"points":7,"pim":0},{"season":20172018,"gameTypeId":2,"leagueAbbrev":"WJC-18","teamName":{"default":"Finland U18"},"sequence":17093,"gamesPlayed":7,"goals":2,"assists":4,"points":6,"plusMinus":1,"pim":2},{"season":20172018,"gameTypeId":2,"leagueAbbrev":"U18 SM-sarja","teamName":{"default":"HIFK U18"},"sequence":25371,"gamesPlayed":10,"goals":3,"assists":7,"points":10,"pim":22},{"season":20172018,"gameTypeId":2,"leagueAbbrev":"U20 SM-sarja","teamName":{"default":"HIFK U20"},"sequence":25390,"gamesPlayed":22,"goals":8,"assists":12,"points":20,"plusMinus":2,"pim":6},{"season":20172018,"gameTypeId":2,"leagueAbbrev":"WHC-17","teamName":{"default":"Finland U17"},"sequence":61280,"gamesPlayed":5,"goals":3,"assists":4,"points":7,"pim":0},{"season":20172018,"gameTypeId":3,"leagueAbbrev":"U18 SM-sarja","teamName":{"default":"HIFK U18"},"sequence":25371,"gamesPlayed":5,"goals":1,"assists":4,"points":5,"pim":8},{"season":20172018,"gameTypeId":3,"leagueAbbrev":"U20 SM-sarja","teamName":{"default":"HIFK U20"},"sequence":25390,"gamesPlayed":9,"goals":1,"assists":1,"points":2,"plusMinus":-2,"pim":4},{"season":20182019,"gameTypeId":2,"leagueAbbrev":"Champions HL","teamName":{"default":"HIFK"},"sequence":492,"gamesPlayed":3,"goals":0,"assists":0,"points":0,"plusMinus":1,"pim":2},{"season":20182019,"gameTypeId":2,"leagueAbbrev":"Liiga","teamName":{"default":"HIFK"},"sequence":869,"gamesPlayed":38,"goals":9,"assists":10,"points":19,"plusMinus":6,"pim":8},{"season":20182019,"gameTypeId":2,"leagueAbbrev":"WJC-18","teamName":{"default":"Finland U18"},"sequence":17093,"gamesPlayed":5,"goals":2,"assists":2,"points":4,"plusMinus":3,"pim":6},{"season":20182019,"gameTypeId":2,"leagueAbbrev":"WJC-20","teamName":{"default":"Finland U20"},"sequence":17116,"gamesPlayed":7,"goals":1,"assists":3,"points":4,"plusMinus":0,"pim":0},{"season":20182019,"gameTypeId":2,"leagueAbbrev":"U20 SM-sarja","teamName":{"default":"HIFK U20"},"sequence":25390,"gamesPlayed":10,"goals":6,"assists":9,"points":15,"plusMinus":11,"pim":6},{"season":20182019,"gameTypeId":2,"leagueAbbrev":"Hlinka Gretzky Cup","teamName":{"default":"Finland U18"},"sequence":158280,"gamesPlayed":4,"goals":1,"assists":1,"points":2,"pim":16},{"season":20182019,"gameTypeId":3,"leagueAbbrev":"Liiga","teamName":{"default":"HIFK"},"sequence":869,"gamesPlayed":12,"goals":0,"assists":0,"points":0,"plusMinus":-2,"pim":29},{"season":20192020,"gameTypeId":2,"leagueAbbrev":"Liiga","teamName":{"default":"HIFK"},"sequence":869,"gamesPlayed":44,"goals":10,"assists":18,"points":28,"plusMinus":11,"pim":18},{"season":20202021,"gameTypeId":2,"leagueAbbrev":"Liiga","teamName":{"default":"HIFK"},"sequence":869,"gamesPlayed":26,"goals":16,"assists":9,"points":25,"plusMinus":9,"pim":12},{"season":20202021,"gameTypeId":2,"leagueAbbrev":"WC","teamName":{"default":"Finland","cs":"Finsko","de":"Finnland","fi":"Suomi","fr":"Finlande","sk":"Fínsko"},"sequence":17055,"gamesPlayed":10,"goals":4,"assists":3,"points":7,"plusMinus":7,"pim":4},{"season":20202021,"gameTypeId":2,"leagueAbbrev":"WJC-20","teamName":{"default":"Finland U20"},"sequence":17116,"gamesPlayed":7,"goals":6,"assists":4,"points":10,"plusMinus":7,"pim":4},{"season":20202021,"gameTypeId":2,"leagueAbbrev":"EHT","teamName":{"default":"Finland","cs":"Finsko","de":"Finnland","fi":"Suomi","fr":"Finlande","sk":"Fínsko"},"sequence":68516,"gamesPlayed":5,"goals":1,"assists":1,"points":2,"plusMinus":-1,"pim":4},{"season":20202021,"gameTypeId":3,"leagueAbbrev":"Liiga","teamName":{"default":"HIFK"},"sequence":869,"gamesPlayed":8,"goals":1,"assists":2,"points":3,"plusMinus":1,"pim":4},{"season":20212022,"gameTypeId":2,"leagueAbbrev":"NHL","teamName":{"default":"Florida Panthers","fr":"Panthers de la Floride"},"sequence":1,"gamesPlayed":65,"goals":18,"assists":26,"points":44,"plusMinus":33,"powerPlayGoals":1,"powerPlayPoints":4,"shorthandedPoints":4,"gameWinningGoals":4,"otGoals":0,"shots":125,"shootingPctg":0.144,"faceoffWinningPctg":0.446524,"avgToi":"15:44","shorthandedGoals":1,"pim":18},{"season":20212022,"gameTypeId":3,"leagueAbbrev":"NHL","teamName":{"default":"Florida Panthers","fr":"Panthers de la Floride"},"sequence":1,"gamesPlayed":9,"goals":1,"assists":0,"points":1,"plusMinus":-1,"powerPlayGoals":0,"powerPlayPoints":0,"shorthandedPoints":0,"gameWinningGoals":0,"otGoals":0,"shots":4,"shootingPctg":0.25,"faceoffWinningPctg":0.533333,"avgToi":"11:30","shorthandedGoals":0,"pim":2},{"season":20222023,"gameTypeId":2,"leagueAbbrev":"NHL","teamName":{"default":"Florida Panthers","fr":"Panthers de la Floride"},"sequence":1,"gamesPlayed":73,"goals":12,"assists":21,"points":33,"plusMinus":1,"powerPlayGoals":0,"powerPlayPoints":5,"shorthandedPoints":2,"gameWinningGoals":1,"otGoals":0,"shots":152,"shootingPctg":0.078947,"faceoffWinningPctg":0.464594,"avgToi":"16:22","shorthandedGoals":2,"pim":43},{"season":20222023,"gameTypeId":3,"leagueAbbrev":"NHL","teamName":{"default":"Florida Panthers","fr":"Panthers de la Floride"},"sequence":1,"gamesPlayed":21,"goals":2,"assists":8,"points":10,"plusMinus":3,"powerPlayGoals":0,"powerPlayPoints":2,"shorthandedPoints":1,"gameWinningGoals":0,"otGoals":0,"shots":43,"shootingPctg":0.046512,"faceoffWinningPctg":0.462963,"avgToi":"18:04","shorthandedGoals":0,"pim":2},{"season":20232024,"gameTypeId":2,"leagueAbbrev":"NHL","teamName":{"default":"Florida Panthers","fr":"Panthers de la Floride"},"sequence":1,"gamesPlayed":30,"goals":2,"assists":10,"points":12,"plusMinus":3,"powerPlayGoals":0,"powerPlayPoints":2,"shorthandedPoints":0,"gameWinningGoals":0,"otGoals":0,"shots":58,"shootingPctg":0.034483,"faceoffWinningPctg":0.506964,"avgToi":"15:27","shorthandedGoals":0,"pim":12}],"currentTeamRoster":[{"playerId":8477493,"lastName":{"default":"Barkov"},"firstName":{"default":"Aleksander"},"playerSlug":"aleksander-barkov-8477493"},{"playerId":8477935,"lastName":{"default":"Bennett"},"firstName":{"default":"Sam"},"playerSlug":"sam-bennett-8477935"},{"playerId":8475683,"lastName":{"default":"Bobrovsky","cs":"Bobrovskij","sk":"Bobrovskij"},"firstName":{"default":"Sergei","cs":"Sergej","sk":"Sergej"},"playerSlug":"sergei-bobrovsky-8475683"},{"playerId":8476393,"lastName":{"default":"Cousins"},"firstName":{"default":"Nick"},"playerSlug":"nick-cousins-8476393"},{"playerId":8477932,"lastName":{"default":"Ekblad"},"firstName":{"default":"Aaron"},"playerSlug":"aaron-ekblad-8477932"},{"playerId":8475171,"lastName":{"default":"Ekman-Larsson"},"firstName":{"default":"Oliver"},"playerSlug":"oliver-ekman-larsson-8475171"},{"playerId":8478055,"lastName":{"default":"Forsling"},"firstName":{"default":"Gustav"},"playerSlug":"gustav-forsling-8478055"},{"playerId":8479981,"lastName":{"default":"Gadjovich"},"firstName":{"default":"Jonah"},"playerSlug":"jonah-gadjovich-8479981"},{"playerId":8475179,"lastName":{"default":"Kulikov"},"firstName":{"default":"Dmitry","cs":"Dmitrij","fi":"Dmitri","sk":"Dmitrij"},"playerSlug":"dmitry-kulikov-8475179"},{"playerId":8479367,"lastName":{"default":"Lockwood"},"firstName":{"default":"William"},"playerSlug":"william-lockwood-8479367"},{"playerId":8479066,"lastName":{"default":"Lomberg"},"firstName":{"default":"Ryan"},"playerSlug":"ryan-lomberg-8479066"},{"playerId":8478904,"lastName":{"default":"Lorentz"},"firstName":{"default":"Steven"},"playerSlug":"steven-lorentz-8478904"},{"playerId":8482113,"lastName":{"default":"Lundell"},"firstName":{"default":"Anton"},"playerSlug":"anton-lundell-8482113"},{"playerId":8480185,"lastName":{"default":"Luostarinen"},"firstName":{"default":"Eetu"},"playerSlug":"eetu-luostarinen-8480185"},{"playerId":8479372,"lastName":{"default":"Mahura"},"firstName":{"default":"Josh"},"playerSlug":"josh-mahura-8479372"},{"playerId":8478859,"lastName":{"default":"Mikkola"},"firstName":{"default":"Niko"},"playerSlug":"niko-mikkola-8478859"},{"playerId":8477986,"lastName":{"default":"Montour"},"firstName":{"default":"Brandon"},"playerSlug":"brandon-montour-8477986"},{"playerId":8477933,"lastName":{"default":"Reinhart"},"firstName":{"default":"Sam"},"playerSlug":"sam-reinhart-8477933"},{"playerId":8478542,"lastName":{"default":"Rodrigues"},"firstName":{"default":"Evan"},"playerSlug":"evan-rodrigues-8478542"},{"playerId":8478831,"lastName":{"default":"Stenlund"},"firstName":{"default":"Kevin"},"playerSlug":"kevin-stenlund-8478831"},{"playerId":8476932,"lastName":{"default":"Stolarz"},"firstName":{"default":"Anthony"},"playerSlug":"anthony-stolarz-8476932"},{"playerId":8479314,"lastName":{"default":"Tkachuk"},"firstName":{"default":"Matthew"},"playerSlug":"matthew-tkachuk-8479314"},{"playerId":8477409,"lastName":{"default":"Verhaeghe"},"firstName":{"default":"Carter"},"playerSlug":"carter-verhaeghe-8477409"}]}