{"playerId":8483436,"isActive":true,"currentTeamId":59,"currentTeamAbbrev":"UTA","fullTeamName":{"default":"Utah Hockey Club","fr":"Club de hockey de l'Utah"},"teamCommonName":{"default":"Utah Hockey Club","fr":"Club de hockey de l'Utah"},"teamPlaceNameWithPreposition":{"default":"Utah","fr":"de l'Utah"},"firstName":{"default":"Artem"},"lastName":{"default":"Duda"},"teamLogo":"https://assets.nhle.com/logos/nhl/svg/UTA_light.svg","position":"D","headshot":"https://assets.nhle.com/mugs/nhl/20242025/UTA/8483436.png","heroImage":"https://assets.nhle.com/mugs/actionshots/1296x729/8483436.jpg","heightInInches":73,"heightInCentimeters":185,"weightInPounds":187,"weightInKilograms":85,"birthDate":"2004-04-08","birthCity":{"default":"Moscow","cs":"Moskva","de":"Moskau","fi":"Moskova","fr":"Moscou","sk":"Moskva","sv":"Moskva"},"birthCountry":"RUS","shootsCatches":"L","draftDetails":{"year":2022,"teamAbbrev":"ARI","round":2,"pickInRound":4,"overallPick":36},"playerSlug":"artem-duda-8483436","inTop100AllTime":0,"inHHOF":0,"shopLink":"#TODO","twitterLink":"#TODO","watchLink":"#TODO","seasonTotals":[{"assists":1,"gameTypeId":2,"gamesPlayed":8,"goals":0,"leagueAbbrev":"WSI U14","points":1,"season":20172018,"sequence":237558,"teamName":{"default":"CSKA Moskva Selects U14"}},{"assists":0,"gameTypeId":2,"gamesPlayed":8,"goals":0,"leagueAbbrev":"WSI U15","pim":0,"points":0,"season":20182019,"sequence":284140,"teamName":{"default":"CSKA Moskva Selects U15"}},{"assists":11,"gameTypeId":2,"gamesPlayed":24,"goals":9,"leagueAbbrev":"Russia U16","pim":4,"points":20,"season":20192020,"sequence":184907,"teamName":{"default":"CSKA Moskva U16"}},{"assists":0,"gameTypeId":2,"gamesPlayed":2,"goals":1,"leagueAbbrev":"Russia U18","pim":0,"points":1,"season":20192020,"sequence":259189,"teamName":{"default":"CSKA Moskva U18"}},{"assists":0,"gameTypeId":2,"gamesPlayed":6,"goals":1,"leagueAbbrev":"WJC-18","pim":0,"plusMinus":1,"points":1,"season":20202021,"sequence":17523,"teamName":{"default":"Russia U18"}},{"assists":8,"gameTypeId":2,"gamesPlayed":40,"goals":1,"leagueAbbrev":"MHL","pim":0,"plusMinus":6,"points":9,"season":20202021,"sequence":49712,"teamName":{"default":"Krasnaya Armiya Moskva"}},{"assists":3,"gameTypeId":2,"gamesPlayed":7,"goals":0,"leagueAbbrev":"Russia U17","pim":2,"points":3,"season":20202021,"sequence":184418,"teamName":{"default":"CSKA Moskva U17"}},{"assists":10,"gameTypeId":2,"gamesPlayed":6,"goals":0,"leagueAbbrev":"Russia U18","pim":0,"points":10,"season":20202021,"sequence":259189,"teamName":{"default":"CSKA Moskva U18"}},{"assists":27,"gameTypeId":2,"gamesPlayed":52,"goals":14,"leagueAbbrev":"MHL","pim":0,"plusMinus":21,"points":41,"season":20212022,"sequence":49712,"teamName":{"default":"Krasnaya Armiya Moskva"}},{"assists":0,"gameTypeId":2,"gamesPlayed":4,"goals":0,"leagueAbbrev":"VHL","pim":0,"plusMinus":-2,"points":0,"season":20212022,"sequence":77127,"teamName":{"default":"Zvezda Moskva"}},{"assists":5,"gameTypeId":2,"gamesPlayed":7,"goals":1,"leagueAbbrev":"Russia U18","points":6,"season":20212022,"sequence":259189,"teamName":{"default":"CSKA Moskva U18"}},{"assists":12,"gameTypeId":3,"gamesPlayed":18,"goals":5,"leagueAbbrev":"MHL","pim":0,"plusMinus":-3,"points":17,"season":20212022,"sequence":49712,"teamName":{"default":"Krasnaya Armiya Moskva"}},{"assists":3,"gameTypeId":2,"gamesPlayed":14,"goals":0,"leagueAbbrev":"KHL","pim":0,"plusMinus":3,"points":3,"season":20222023,"sequence":2314,"teamName":{"default":"CSKA Moskva"}},{"assists":8,"gameTypeId":2,"gamesPlayed":14,"goals":5,"leagueAbbrev":"MHL","pim":2,"plusMinus":1,"points":13,"season":20222023,"sequence":49712,"teamName":{"default":"Krasnaya Armiya Moskva"}},{"assists":0,"gameTypeId":2,"gamesPlayed":3,"goals":0,"leagueAbbrev":"VHL","pim":0,"plusMinus":0,"points":0,"season":20222023,"sequence":77127,"teamName":{"default":"Zvezda Moskva"}},{"assists":0,"gameTypeId":3,"gamesPlayed":4,"goals":0,"leagueAbbrev":"MHL","pim":0,"plusMinus":0,"points":0,"season":20222023,"sequence":49712,"teamName":{"default":"Krasnaya Armiya Moskva"}},{"assists":5,"gameTypeId":2,"gamesPlayed":12,"goals":2,"leagueAbbrev":"USports","pim":10,"points":7,"season":20232024,"sequence":34912,"teamName":{"default":"Toronto Metro Univ."}},{"assists":4,"gameTypeId":3,"gamesPlayed":6,"goals":2,"leagueAbbrev":"USports","pim":0,"points":6,"season":20232024,"sequence":34912,"teamName":{"default":"Toronto Metro Univ."}}],"currentTeamRoster":[{"playerId":8475461,"lastName":{"default":"Agozzino"},"firstName":{"default":"Andrew"},"playerSlug":"andrew-agozzino-8475461"},{"playerId":8479561,"lastName":{"default":"Barron"},"firstName":{"default":"Travis"},"playerSlug":"travis-barron-8479561"},{"playerId":8484786,"lastName":{"default":"Beaudoin"},"firstName":{"default":"Cole"},"playerSlug":"cole-beaudoin-8484786"},{"playerId":8475760,"lastName":{"default":"Bjugstad"},"firstName":{"default":"Nick"},"playerSlug":"nick-bjugstad-8475760"},{"playerId":8474145,"lastName":{"default":"Bortuzzo"},"firstName":{"default":"Robert"},"playerSlug":"robert-bortuzzo-8474145"},{"playerId":8479619,"lastName":{"default":"Carcone"},"firstName":{"default":"Michael"},"playerSlug":"michael-carcone-8479619"},{"playerId":8474013,"lastName":{"default":"Cole"},"firstName":{"default":"Ian"},"playerSlug":"ian-cole-8474013"},{"playerId":8475246,"lastName":{"default":"Connauton"},"firstName":{"default":"Kevin"},"playerSlug":"kevin-connauton-8475246"},{"playerId":8483431,"lastName":{"default":"Cooley"},"firstName":{"default":"Logan"},"playerSlug":"logan-cooley-8483431"},{"playerId":8478474,"lastName":{"default":"Crouse"},"firstName":{"default":"Lawson"},"playerSlug":"lawson-crouse-8478474"},{"playerId":8482659,"lastName":{"default":"Doan"},"firstName":{"default":"Josh"},"playerSlug":"josh-doan-8482659"},{"playerId":8480876,"lastName":{"default":"Douglas"},"firstName":{"default":"Curtis"},"playerSlug":"curtis-douglas-8480876"},{"playerId":8483436,"lastName":{"default":"Duda"},"firstName":{"default":"Artem"},"playerSlug":"artem-duda-8483436"},{"playerId":8480434,"lastName":{"default":"Durzi"},"firstName":{"default":"Sean"},"playerSlug":"sean-durzi-8480434"},{"playerId":8482699,"lastName":{"default":"Guenther"},"firstName":{"default":"Dylan"},"playerSlug":"dylan-guenther-8482699"},{"playerId":8480849,"lastName":{"default":"Hayton"},"firstName":{"default":"Barrett"},"playerSlug":"barrett-hayton-8480849"},{"playerId":8484795,"lastName":{"default":"Iginla"},"firstName":{"default":"Tij"},"playerSlug":"tij-iginla-8484795"},{"playerId":8478971,"lastName":{"default":"Ingram"},"firstName":{"default":"Connor"},"playerSlug":"connor-ingram-8478971"},{"playerId":8483597,"lastName":{"default":"Kelemen"},"firstName":{"default":"Milos"},"playerSlug":"milos-kelemen-8483597"},{"playerId":8479343,"lastName":{"default":"Keller"},"firstName":{"default":"Clayton"},"playerSlug":"clayton-keller-8479343"},{"playerId":8477021,"lastName":{"default":"Kerfoot"},"firstName":{"default":"Alex","cs":"Alexander","de":"Alexander","es":"Alexander","fi":"Alexander","sk":"Alexander","sv":"Alexander"},"playerSlug":"alex-kerfoot-8477021"},{"playerId":8480891,"lastName":{"default":"Kesselring"},"firstName":{"default":"Michael"},"playerSlug":"michael-kesselring-8480891"},{"playerId":8484326,"lastName":{"default":"Koch"},"firstName":{"default":"Patrik"},"playerSlug":"patrik-koch-8484326"},{"playerId":8481609,"lastName":{"default":"Kolyachonok","cs":"Koljačonok","sk":"Koljačonok"},"firstName":{"default":"Vladislav"},"playerSlug":"vladislav-kolyachonok-8481609"},{"playerId":8483472,"lastName":{"default":"Lamoureux"},"firstName":{"default":"Maveric"},"playerSlug":"maveric-lamoureux-8483472"},{"playerId":8482924,"lastName":{"default":"Lipkin"},"firstName":{"default":"Sam"},"playerSlug":"sam-lipkin-8482924"},{"playerId":8481711,"lastName":{"default":"Maccelli"},"firstName":{"default":"Matias"},"playerSlug":"matias-maccelli-8481711"},{"playerId":8478507,"lastName":{"default":"Marino"},"firstName":{"default":"John"},"playerSlug":"john-marino-8478507"},{"playerId":8483671,"lastName":{"default":"Matikka"},"firstName":{"default":"Miko"},"playerSlug":"miko-matikka-8483671"},{"playerId":8480855,"lastName":{"default":"McBain"},"firstName":{"default":"Jack"},"playerSlug":"jack-mcbain-8480855"},{"playerId":8481827,"lastName":{"default":"McCartney"},"firstName":{"default":"Ben"},"playerSlug":"ben-mccartney-8481827"},{"playerId":8484207,"lastName":{"default":"Nordh"},"firstName":{"default":"Noel"},"playerSlug":"noel-nordh-8484207"},{"playerId":8477070,"lastName":{"default":"O'Brien"},"firstName":{"default":"Liam"},"playerSlug":"liam-o-brien-8477070"},{"playerId":8481159,"lastName":{"default":"Onyebuchi"},"firstName":{"default":"Montana"},"playerSlug":"montana-onyebuchi-8481159"},{"playerId":8481699,"lastName":{"default":"Raty"},"firstName":{"default":"Aku"},"playerSlug":"aku-raty-8481699"},{"playerId":8477951,"lastName":{"default":"Schmaltz"},"firstName":{"default":"Nick"},"playerSlug":"nick-schmaltz-8477951"},{"playerId":8479410,"lastName":{"default":"Sergachev","cs":"Sergačov","fi":"Sergatshov","sk":"Sergačov"},"firstName":{"default":"Mikhail","cs":"Michail","fi":"Mihail","sk":"Michail"},"playerSlug":"mikhail-sergachev-8479410"},{"playerId":8481102,"lastName":{"default":"Sokolov"},"firstName":{"default":"Egor"},"playerSlug":"egor-sokolov-8481102"},{"playerId":8483530,"lastName":{"default":"Stauber"},"firstName":{"default":"Jaxson"},"playerSlug":"jaxson-stauber-8483530"},{"playerId":8478831,"lastName":{"default":"Stenlund"},"firstName":{"default":"Kevin"},"playerSlug":"kevin-stenlund-8478831"},{"playerId":8483763,"lastName":{"default":"Szuber"},"firstName":{"default":"Maksymilian"},"playerSlug":"maksymilian-szuber-8483763"},{"playerId":8483099,"lastName":{"default":"Thornton"},"firstName":{"default":"Anson"},"playerSlug":"anson-thornton-8483099"},{"playerId":8479976,"lastName":{"default":"Valimaki","cs":"Välimäki","fi":"Välimäki","sk":"Välimäki"},"firstName":{"default":"Juuso"},"playerSlug":"juuso-valimaki-8479976"},{"playerId":8478872,"lastName":{"default":"Vejmelka"},"firstName":{"default":"Karel"},"playerSlug":"karel-vejmelka-8478872"},{"playerId":8480191,"lastName":{"default":"Villalta"},"firstName":{"default":"Matt"},"playerSlug":"matt-villalta-8480191"}]}